ChillBot/__init__.py
ChillBot/base_urls.py
ChillBot/exceptions.py
ChillBot/music.py
ChillBot/requests.py
ChillBot.py-1.1.2.dist-info/LICENSE
ChillBot.py-1.1.2.dist-info/METADATA
ChillBot.py-1.1.2.dist-info/WHEEL
ChillBot.py-1.1.2.dist-info/top_level.txt
ChillBot.py-1.1.2.dist-info/RECORD
