Metadata-Version: 2.1
Name: ChillBot.py
Version: 1.1.2
Summary: An API wrapper for ChillBot's API
Author: RainzDev
Author-email: jessrblx16@gmail.com
Project-URL: Homepage, https://github.com/RainzDev/ChillBot.py
Project-URL: Documentation, https://chillbotpy.readthedocs.io/en/latest/index.html
Requires-Python: >=3.10
License-File: LICENSE
Requires-Dist: aiohttp
